<?xml version="1.0" encoding="utf-8" standalone="yes"?>
<Gesture Name="delete_mark05" Subject="1" Speed="medium" Number="5" NumPts="577" Millseconds="1220" AppName="GestureCapture" AppVer="1.0.0.0" Date="Tuesday, June 16, 2026" TimeOfDay="01:34:01 PM">
<Point X="415" Y="223" T="1781609641554" />
<Point X="415" Y="224" T="1781609641577" />
<Point X="415" Y="224" T="1781609641578" />
<Point X="415" Y="225" T="1781609641585" />
<Point X="416" Y="225" T="1781609641587" />
<Point X="416" Y="225" T="1781609641589" />
<Point X="416" Y="225" T="1781609641605" />
<Point X="417" Y="226" T="1781609641605" />
<Point X="417" Y="226" T="1781609641606" />
<Point X="417" Y="226" T="1781609641606" />
<Point X="417" Y="227" T="1781609641606" />
<Point X="417" Y="227" T="1781609641606" />
<Point X="418" Y="227" T="1781609641606" />
<Point X="418" Y="228" T="1781609641606" />
<Point X="418" Y="228" T="1781609641606" />
<Point X="419" Y="228" T="1781609641606" />
<Point X="419" Y="229" T="1781609641606" />
<Point X="419" Y="229" T="1781609641607" />
<Point X="420" Y="229" T="1781609641607" />
<Point X="420" Y="230" T="1781609641607" />
<Point X="420" Y="230" T="1781609641622" />
<Point X="420" Y="230" T="1781609641622" />
<Point X="420" Y="230" T="1781609641622" />
<Point X="420" Y="231" T="1781609641622" />
<Point X="421" Y="231" T="1781609641622" />
<Point X="421" Y="231" T="1781609641622" />
<Point X="421" Y="232" T="1781609641622" />
<Point X="422" Y="232" T="1781609641623" />
<Point X="422" Y="233" T="1781609641623" />
<Point X="422" Y="233" T="1781609641623" />
<Point X="422" Y="233" T="1781609641623" />
<Point X="423" Y="234" T="1781609641623" />
<Point X="423" Y="234" T="1781609641623" />
<Point X="423" Y="235" T="1781609641623" />
<Point X="424" Y="235" T="1781609641624" />
<Point X="424" Y="235" T="1781609641639" />
<Point X="424" Y="235" T="1781609641639" />
<Point X="425" Y="236" T="1781609641639" />
<Point X="425" Y="236" T="1781609641639" />
<Point X="425" Y="237" T="1781609641640" />
<Point X="425" Y="237" T="1781609641640" />
<Point X="426" Y="238" T="1781609641640" />
<Point X="426" Y="238" T="1781609641640" />
<Point X="427" Y="238" T="1781609641640" />
<Point X="427" Y="239" T="1781609641640" />
<Point X="427" Y="240" T="1781609641640" />
<Point X="427" Y="240" T="1781609641641" />
<Point X="428" Y="240" T="1781609641641" />
<Point X="428" Y="241" T="1781609641641" />
<Point X="429" Y="242" T="1781609641641" />
<Point X="429" Y="242" T="1781609641641" />
<Point X="430" Y="243" T="1781609641641" />
<Point X="430" Y="243" T="1781609641641" />
<Point X="431" Y="244" T="1781609641655" />
<Point X="431" Y="245" T="1781609641656" />
<Point X="431" Y="245" T="1781609641656" />
<Point X="432" Y="246" T="1781609641656" />
<Point X="432" Y="246" T="1781609641656" />
<Point X="433" Y="247" T="1781609641656" />
<Point X="433" Y="248" T="1781609641656" />
<Point X="434" Y="248" T="1781609641656" />
<Point X="434" Y="249" T="1781609641657" />
<Point X="435" Y="250" T="1781609641657" />
<Point X="435" Y="250" T="1781609641657" />
<Point X="436" Y="251" T="1781609641657" />
<Point X="436" Y="251" T="1781609641657" />
<Point X="437" Y="252" T="1781609641657" />
<Point X="438" Y="253" T="1781609641657" />
<Point X="438" Y="254" T="1781609641657" />
<Point X="438" Y="254" T="1781609641672" />
<Point X="439" Y="255" T="1781609641672" />
<Point X="439" Y="256" T="1781609641673" />
<Point X="440" Y="256" T="1781609641673" />
<Point X="441" Y="257" T="1781609641673" />
<Point X="441" Y="257" T="1781609641673" />
<Point X="442" Y="258" T="1781609641673" />
<Point X="442" Y="259" T="1781609641673" />
<Point X="443" Y="259" T="1781609641673" />
<Point X="443" Y="260" T="1781609641673" />
<Point X="444" Y="261" T="1781609641674" />
<Point X="444" Y="262" T="1781609641674" />
<Point X="445" Y="262" T="1781609641674" />
<Point X="446" Y="263" T="1781609641674" />
<Point X="447" Y="264" T="1781609641674" />
<Point X="447" Y="265" T="1781609641674" />
<Point X="447" Y="265" T="1781609641674" />
<Point X="448" Y="266" T="1781609641688" />
<Point X="449" Y="267" T="1781609641689" />
<Point X="449" Y="268" T="1781609641689" />
<Point X="450" Y="268" T="1781609641689" />
<Point X="451" Y="269" T="1781609641689" />
<Point X="452" Y="270" T="1781609641689" />
<Point X="452" Y="271" T="1781609641689" />
<Point X="453" Y="271" T="1781609641689" />
<Point X="453" Y="272" T="1781609641689" />
<Point X="454" Y="273" T="1781609641690" />
<Point X="455" Y="273" T="1781609641690" />
<Point X="455" Y="274" T="1781609641690" />
<Point X="456" Y="275" T="1781609641690" />
<Point X="457" Y="276" T="1781609641690" />
<Point X="457" Y="276" T="1781609641690" />
<Point X="458" Y="277" T="1781609641690" />
<Point X="459" Y="278" T="1781609641705" />
<Point X="459" Y="279" T="1781609641705" />
<Point X="461" Y="280" T="1781609641705" />
<Point X="461" Y="281" T="1781609641706" />
<Point X="462" Y="282" T="1781609641706" />
<Point X="463" Y="282" T="1781609641706" />
<Point X="463" Y="283" T="1781609641706" />
<Point X="464" Y="284" T="1781609641706" />
<Point X="465" Y="285" T="1781609641706" />
<Point X="466" Y="286" T="1781609641706" />
<Point X="467" Y="287" T="1781609641707" />
<Point X="468" Y="288" T="1781609641707" />
<Point X="468" Y="289" T="1781609641707" />
<Point X="469" Y="289" T="1781609641707" />
<Point X="470" Y="290" T="1781609641707" />
<Point X="471" Y="291" T="1781609641707" />
<Point X="472" Y="292" T="1781609641707" />
<Point X="473" Y="293" T="1781609641723" />
<Point X="474" Y="294" T="1781609641723" />
<Point X="475" Y="295" T="1781609641724" />
<Point X="476" Y="296" T="1781609641724" />
<Point X="477" Y="296" T="1781609641724" />
<Point X="478" Y="297" T="1781609641724" />
<Point X="479" Y="298" T="1781609641724" />
<Point X="479" Y="299" T="1781609641724" />
<Point X="480" Y="300" T="1781609641725" />
<Point X="481" Y="301" T="1781609641725" />
<Point X="482" Y="302" T="1781609641725" />
<Point X="483" Y="303" T="1781609641725" />
<Point X="484" Y="304" T="1781609641725" />
<Point X="485" Y="304" T="1781609641725" />
<Point X="486" Y="306" T="1781609641725" />
<Point X="487" Y="306" T="1781609641725" />
<Point X="488" Y="307" T="1781609641726" />
<Point X="489" Y="308" T="1781609641726" />
<Point X="489" Y="308" T="1781609641739" />
<Point X="490" Y="309" T="1781609641739" />
<Point X="491" Y="310" T="1781609641740" />
<Point X="492" Y="311" T="1781609641740" />
<Point X="493" Y="312" T="1781609641740" />
<Point X="494" Y="312" T="1781609641740" />
<Point X="495" Y="313" T="1781609641740" />
<Point X="496" Y="314" T="1781609641740" />
<Point X="497" Y="315" T="1781609641740" />
<Point X="497" Y="315" T="1781609641740" />
<Point X="498" Y="315" T="1781609641740" />
<Point X="499" Y="316" T="1781609641741" />
<Point X="500" Y="317" T="1781609641741" />
<Point X="500" Y="318" T="1781609641741" />
<Point X="501" Y="318" T="1781609641741" />
<Point X="502" Y="318" T="1781609641741" />
<Point X="503" Y="319" T="1781609641755" />
<Point X="503" Y="320" T="1781609641755" />
<Point X="504" Y="320" T="1781609641756" />
<Point X="505" Y="321" T="1781609641756" />
<Point X="506" Y="321" T="1781609641756" />
<Point X="506" Y="321" T="1781609641756" />
<Point X="507" Y="322" T="1781609641756" />
<Point X="508" Y="322" T="1781609641756" />
<Point X="508" Y="323" T="1781609641757" />
<Point X="509" Y="323" T="1781609641757" />
<Point X="510" Y="324" T="1781609641757" />
<Point X="510" Y="324" T="1781609641757" />
<Point X="511" Y="324" T="1781609641757" />
<Point X="511" Y="324" T="1781609641757" />
<Point X="512" Y="325" T="1781609641757" />
<Point X="513" Y="325" T="1781609641757" />
<Point X="513" Y="326" T="1781609641772" />
<Point X="514" Y="326" T="1781609641772" />
<Point X="514" Y="326" T="1781609641772" />
<Point X="515" Y="326" T="1781609641773" />
<Point X="515" Y="326" T="1781609641773" />
<Point X="516" Y="327" T="1781609641773" />
<Point X="516" Y="327" T="1781609641773" />
<Point X="516" Y="327" T="1781609641773" />
<Point X="517" Y="328" T="1781609641773" />
<Point X="518" Y="328" T="1781609641773" />
<Point X="518" Y="328" T="1781609641774" />
<Point X="518" Y="328" T="1781609641774" />
<Point X="518" Y="328" T="1781609641774" />
<Point X="519" Y="329" T="1781609641774" />
<Point X="519" Y="329" T="1781609641774" />
<Point X="520" Y="329" T="1781609641774" />
<Point X="520" Y="329" T="1781609641774" />
<Point X="521" Y="329" T="1781609641789" />
<Point X="521" Y="330" T="1781609641789" />
<Point X="521" Y="330" T="1781609641789" />
<Point X="522" Y="330" T="1781609641790" />
<Point X="522" Y="330" T="1781609641790" />
<Point X="523" Y="331" T="1781609641790" />
<Point X="523" Y="331" T="1781609641790" />
<Point X="523" Y="331" T="1781609641790" />
<Point X="524" Y="331" T="1781609641805" />
<Point X="524" Y="331" T="1781609641805" />
<Point X="524" Y="332" T="1781609641822" />
<Point X="524" Y="332" T="1781609642092" />
<Point X="524" Y="332" T="1781609642094" />
<Point X="524" Y="332" T="1781609642095" />
<Point X="524" Y="333" T="1781609642097" />
<Point X="523" Y="333" T="1781609642107" />
<Point X="523" Y="333" T="1781609642108" />
<Point X="522" Y="333" T="1781609642108" />
<Point X="522" Y="333" T="1781609642108" />
<Point X="521" Y="333" T="1781609642108" />
<Point X="521" Y="333" T="1781609642108" />
<Point X="520" Y="334" T="1781609642108" />
<Point X="520" Y="334" T="1781609642108" />
<Point X="519" Y="334" T="1781609642109" />
<Point X="518" Y="335" T="1781609642109" />
<Point X="518" Y="335" T="1781609642109" />
<Point X="517" Y="335" T="1781609642109" />
<Point X="516" Y="335" T="1781609642109" />
<Point X="515" Y="336" T="1781609642123" />
<Point X="515" Y="336" T="1781609642124" />
<Point X="514" Y="337" T="1781609642124" />
<Point X="513" Y="337" T="1781609642124" />
<Point X="512" Y="337" T="1781609642124" />
<Point X="511" Y="338" T="1781609642125" />
<Point X="510" Y="338" T="1781609642125" />
<Point X="509" Y="338" T="1781609642125" />
<Point X="509" Y="339" T="1781609642125" />
<Point X="507" Y="339" T="1781609642125" />
<Point X="506" Y="339" T="1781609642125" />
<Point X="506" Y="340" T="1781609642126" />
<Point X="505" Y="340" T="1781609642126" />
<Point X="503" Y="341" T="1781609642126" />
<Point X="502" Y="341" T="1781609642126" />
<Point X="502" Y="341" T="1781609642126" />
<Point X="501" Y="341" T="1781609642126" />
<Point X="500" Y="342" T="1781609642141" />
<Point X="499" Y="342" T="1781609642141" />
<Point X="498" Y="343" T="1781609642141" />
<Point X="496" Y="343" T="1781609642142" />
<Point X="496" Y="343" T="1781609642142" />
<Point X="495" Y="344" T="1781609642142" />
<Point X="493" Y="344" T="1781609642142" />
<Point X="492" Y="344" T="1781609642142" />
<Point X="491" Y="345" T="1781609642143" />
<Point X="490" Y="345" T="1781609642143" />
<Point X="489" Y="345" T="1781609642143" />
<Point X="487" Y="345" T="1781609642143" />
<Point X="487" Y="346" T="1781609642143" />
<Point X="485" Y="346" T="1781609642143" />
<Point X="484" Y="346" T="1781609642143" />
<Point X="483" Y="347" T="1781609642144" />
<Point X="482" Y="347" T="1781609642144" />
<Point X="481" Y="347" T="1781609642144" />
<Point X="479" Y="348" T="1781609642156" />
<Point X="478" Y="348" T="1781609642157" />
<Point X="477" Y="348" T="1781609642157" />
<Point X="476" Y="348" T="1781609642157" />
<Point X="474" Y="349" T="1781609642157" />
<Point X="473" Y="349" T="1781609642157" />
<Point X="471" Y="349" T="1781609642157" />
<Point X="470" Y="350" T="1781609642158" />
<Point X="469" Y="350" T="1781609642158" />
<Point X="468" Y="350" T="1781609642158" />
<Point X="467" Y="350" T="1781609642158" />
<Point X="465" Y="350" T="1781609642158" />
<Point X="464" Y="351" T="1781609642158" />
<Point X="463" Y="351" T="1781609642159" />
<Point X="462" Y="351" T="1781609642173" />
<Point X="460" Y="351" T="1781609642173" />
<Point X="459" Y="352" T="1781609642174" />
<Point X="458" Y="352" T="1781609642174" />
<Point X="457" Y="352" T="1781609642174" />
<Point X="455" Y="353" T="1781609642174" />
<Point X="454" Y="353" T="1781609642174" />
<Point X="453" Y="353" T="1781609642175" />
<Point X="452" Y="354" T="1781609642175" />
<Point X="451" Y="354" T="1781609642175" />
<Point X="449" Y="354" T="1781609642175" />
<Point X="448" Y="355" T="1781609642175" />
<Point X="447" Y="355" T="1781609642175" />
<Point X="446" Y="355" T="1781609642176" />
<Point X="445" Y="355" T="1781609642176" />
<Point X="444" Y="356" T="1781609642176" />
<Point X="443" Y="356" T="1781609642176" />
<Point X="441" Y="356" T="1781609642176" />
<Point X="440" Y="356" T="1781609642190" />
<Point X="439" Y="356" T="1781609642191" />
<Point X="438" Y="356" T="1781609642191" />
<Point X="437" Y="357" T="1781609642191" />
<Point X="436" Y="357" T="1781609642191" />
<Point X="435" Y="357" T="1781609642191" />
<Point X="434" Y="358" T="1781609642192" />
<Point X="433" Y="358" T="1781609642192" />
<Point X="432" Y="358" T="1781609642192" />
<Point X="431" Y="358" T="1781609642192" />
<Point X="430" Y="359" T="1781609642192" />
<Point X="429" Y="359" T="1781609642192" />
<Point X="428" Y="359" T="1781609642193" />
<Point X="427" Y="359" T="1781609642193" />
<Point X="426" Y="360" T="1781609642193" />
<Point X="425" Y="360" T="1781609642193" />
<Point X="424" Y="360" T="1781609642193" />
<Point X="423" Y="360" T="1781609642206" />
<Point X="422" Y="360" T="1781609642206" />
<Point X="421" Y="360" T="1781609642207" />
<Point X="420" Y="360" T="1781609642207" />
<Point X="419" Y="361" T="1781609642207" />
<Point X="418" Y="361" T="1781609642207" />
<Point X="417" Y="361" T="1781609642207" />
<Point X="416" Y="362" T="1781609642207" />
<Point X="415" Y="362" T="1781609642208" />
<Point X="415" Y="362" T="1781609642208" />
<Point X="413" Y="362" T="1781609642208" />
<Point X="412" Y="363" T="1781609642208" />
<Point X="412" Y="363" T="1781609642208" />
<Point X="411" Y="363" T="1781609642208" />
<Point X="410" Y="363" T="1781609642208" />
<Point X="409" Y="363" T="1781609642223" />
<Point X="408" Y="363" T="1781609642224" />
<Point X="407" Y="364" T="1781609642224" />
<Point X="407" Y="364" T="1781609642224" />
<Point X="406" Y="364" T="1781609642224" />
<Point X="405" Y="364" T="1781609642225" />
<Point X="404" Y="365" T="1781609642225" />
<Point X="404" Y="365" T="1781609642225" />
<Point X="403" Y="365" T="1781609642225" />
<Point X="402" Y="365" T="1781609642225" />
<Point X="401" Y="365" T="1781609642225" />
<Point X="400" Y="365" T="1781609642225" />
<Point X="399" Y="365" T="1781609642226" />
<Point X="399" Y="366" T="1781609642226" />
<Point X="398" Y="366" T="1781609642226" />
<Point X="397" Y="366" T="1781609642226" />
<Point X="397" Y="366" T="1781609642226" />
<Point X="396" Y="367" T="1781609642227" />
<Point X="395" Y="367" T="1781609642242" />
<Point X="395" Y="367" T="1781609642243" />
<Point X="394" Y="367" T="1781609642243" />
<Point X="394" Y="367" T="1781609642243" />
<Point X="393" Y="367" T="1781609642244" />
<Point X="392" Y="367" T="1781609642244" />
<Point X="392" Y="368" T="1781609642244" />
<Point X="391" Y="368" T="1781609642244" />
<Point X="390" Y="368" T="1781609642244" />
<Point X="390" Y="368" T="1781609642245" />
<Point X="389" Y="368" T="1781609642245" />
<Point X="389" Y="368" T="1781609642245" />
<Point X="388" Y="368" T="1781609642245" />
<Point X="387" Y="368" T="1781609642245" />
<Point X="387" Y="368" T="1781609642246" />
<Point X="387" Y="368" T="1781609642246" />
<Point X="386" Y="368" T="1781609642246" />
<Point X="385" Y="369" T="1781609642246" />
<Point X="385" Y="369" T="1781609642246" />
<Point X="384" Y="369" T="1781609642246" />
<Point X="384" Y="369" T="1781609642259" />
<Point X="384" Y="369" T="1781609642260" />
<Point X="383" Y="369" T="1781609642260" />
<Point X="382" Y="369" T="1781609642260" />
<Point X="382" Y="369" T="1781609642260" />
<Point X="382" Y="369" T="1781609642261" />
<Point X="381" Y="369" T="1781609642261" />
<Point X="381" Y="369" T="1781609642261" />
<Point X="380" Y="369" T="1781609642261" />
<Point X="380" Y="369" T="1781609642261" />
<Point X="379" Y="369" T="1781609642261" />
<Point X="379" Y="370" T="1781609642262" />
<Point X="379" Y="370" T="1781609642262" />
<Point X="379" Y="370" T="1781609642262" />
<Point X="378" Y="370" T="1781609642263" />
<Point X="378" Y="370" T="1781609642263" />
<Point X="377" Y="370" T="1781609642275" />
<Point X="377" Y="370" T="1781609642275" />
<Point X="377" Y="370" T="1781609642276" />
<Point X="376" Y="370" T="1781609642276" />
<Point X="376" Y="370" T="1781609642276" />
<Point X="375" Y="370" T="1781609642276" />
<Point X="375" Y="370" T="1781609642276" />
<Point X="374" Y="370" T="1781609642277" />
<Point X="374" Y="370" T="1781609642292" />
<Point X="374" Y="370" T="1781609642293" />
<Point X="373" Y="370" T="1781609642293" />
<Point X="373" Y="370" T="1781609642293" />
<Point X="373" Y="370" T="1781609642293" />
<Point X="372" Y="370" T="1781609642307" />
<Point X="372" Y="369" T="1781609642544" />
<Point X="373" Y="369" T="1781609642548" />
<Point X="373" Y="369" T="1781609642550" />
<Point X="373" Y="368" T="1781609642551" />
<Point X="373" Y="368" T="1781609642560" />
<Point X="373" Y="368" T="1781609642560" />
<Point X="373" Y="368" T="1781609642561" />
<Point X="374" Y="367" T="1781609642561" />
<Point X="374" Y="366" T="1781609642561" />
<Point X="375" Y="365" T="1781609642561" />
<Point X="375" Y="365" T="1781609642562" />
<Point X="375" Y="365" T="1781609642562" />
<Point X="375" Y="364" T="1781609642562" />
<Point X="376" Y="364" T="1781609642562" />
<Point X="376" Y="363" T="1781609642590" />
<Point X="377" Y="363" T="1781609642590" />
<Point X="377" Y="362" T="1781609642590" />
<Point X="378" Y="361" T="1781609642591" />
<Point X="378" Y="361" T="1781609642591" />
<Point X="378" Y="360" T="1781609642591" />
<Point X="379" Y="360" T="1781609642591" />
<Point X="380" Y="359" T="1781609642591" />
<Point X="380" Y="359" T="1781609642592" />
<Point X="380" Y="358" T="1781609642592" />
<Point X="381" Y="358" T="1781609642592" />
<Point X="381" Y="357" T="1781609642592" />
<Point X="382" Y="356" T="1781609642592" />
<Point X="382" Y="356" T="1781609642592" />
<Point X="383" Y="355" T="1781609642593" />
<Point X="383" Y="355" T="1781609642593" />
<Point X="384" Y="354" T="1781609642593" />
<Point X="385" Y="353" T="1781609642593" />
<Point X="385" Y="352" T="1781609642593" />
<Point X="386" Y="352" T="1781609642594" />
<Point X="386" Y="351" T="1781609642594" />
<Point X="387" Y="350" T="1781609642594" />
<Point X="388" Y="350" T="1781609642594" />
<Point X="388" Y="349" T="1781609642594" />
<Point X="389" Y="348" T="1781609642595" />
<Point X="390" Y="348" T="1781609642595" />
<Point X="390" Y="347" T="1781609642595" />
<Point X="391" Y="346" T="1781609642595" />
<Point X="392" Y="345" T="1781609642595" />
<Point X="392" Y="345" T="1781609642596" />
<Point X="393" Y="344" T="1781609642596" />
<Point X="394" Y="343" T="1781609642596" />
<Point X="395" Y="342" T="1781609642596" />
<Point X="395" Y="342" T="1781609642596" />
<Point X="396" Y="341" T="1781609642605" />
<Point X="397" Y="340" T="1781609642606" />
<Point X="397" Y="339" T="1781609642606" />
<Point X="398" Y="339" T="1781609642607" />
<Point X="399" Y="338" T="1781609642607" />
<Point X="400" Y="337" T="1781609642607" />
<Point X="401" Y="336" T="1781609642607" />
<Point X="401" Y="336" T="1781609642607" />
<Point X="402" Y="335" T="1781609642608" />
<Point X="403" Y="334" T="1781609642608" />
<Point X="403" Y="333" T="1781609642608" />
<Point X="404" Y="333" T="1781609642608" />
<Point X="405" Y="332" T="1781609642622" />
<Point X="406" Y="331" T="1781609642623" />
<Point X="407" Y="331" T="1781609642623" />
<Point X="407" Y="330" T="1781609642623" />
<Point X="408" Y="329" T="1781609642623" />
<Point X="409" Y="328" T="1781609642624" />
<Point X="410" Y="328" T="1781609642624" />
<Point X="411" Y="327" T="1781609642624" />
<Point X="411" Y="326" T="1781609642624" />
<Point X="413" Y="326" T="1781609642624" />
<Point X="413" Y="325" T="1781609642624" />
<Point X="414" Y="324" T="1781609642625" />
<Point X="415" Y="323" T="1781609642625" />
<Point X="416" Y="322" T="1781609642625" />
<Point X="417" Y="321" T="1781609642625" />
<Point X="418" Y="321" T="1781609642626" />
<Point X="418" Y="320" T="1781609642626" />
<Point X="419" Y="319" T="1781609642626" />
<Point X="420" Y="318" T="1781609642639" />
<Point X="421" Y="317" T="1781609642639" />
<Point X="422" Y="316" T="1781609642639" />
<Point X="423" Y="316" T="1781609642640" />
<Point X="424" Y="315" T="1781609642640" />
<Point X="425" Y="314" T="1781609642640" />
<Point X="426" Y="313" T="1781609642640" />
<Point X="427" Y="312" T="1781609642641" />
<Point X="428" Y="311" T="1781609642641" />
<Point X="429" Y="310" T="1781609642641" />
<Point X="430" Y="309" T="1781609642641" />
<Point X="431" Y="308" T="1781609642642" />
<Point X="432" Y="307" T="1781609642642" />
<Point X="433" Y="307" T="1781609642642" />
<Point X="434" Y="305" T="1781609642642" />
<Point X="436" Y="304" T="1781609642642" />
<Point X="437" Y="303" T="1781609642655" />
<Point X="438" Y="302" T="1781609642656" />
<Point X="439" Y="301" T="1781609642656" />
<Point X="440" Y="300" T="1781609642656" />
<Point X="441" Y="299" T="1781609642656" />
<Point X="442" Y="298" T="1781609642657" />
<Point X="443" Y="297" T="1781609642657" />
<Point X="445" Y="296" T="1781609642657" />
<Point X="445" Y="294" T="1781609642657" />
<Point X="447" Y="293" T="1781609642658" />
<Point X="447" Y="292" T="1781609642658" />
<Point X="449" Y="291" T="1781609642658" />
<Point X="450" Y="290" T="1781609642658" />
<Point X="451" Y="289" T="1781609642659" />
<Point X="452" Y="287" T="1781609642659" />
<Point X="454" Y="286" T="1781609642659" />
<Point X="455" Y="285" T="1781609642659" />
<Point X="455" Y="284" T="1781609642672" />
<Point X="456" Y="283" T="1781609642672" />
<Point X="457" Y="282" T="1781609642673" />
<Point X="458" Y="281" T="1781609642673" />
<Point X="460" Y="280" T="1781609642673" />
<Point X="461" Y="279" T="1781609642673" />
<Point X="462" Y="278" T="1781609642673" />
<Point X="463" Y="277" T="1781609642674" />
<Point X="464" Y="275" T="1781609642674" />
<Point X="465" Y="274" T="1781609642674" />
<Point X="466" Y="273" T="1781609642674" />
<Point X="468" Y="272" T="1781609642674" />
<Point X="469" Y="270" T="1781609642675" />
<Point X="470" Y="270" T="1781609642675" />
<Point X="471" Y="269" T="1781609642675" />
<Point X="472" Y="267" T="1781609642675" />
<Point X="473" Y="266" T="1781609642689" />
<Point X="474" Y="265" T="1781609642690" />
<Point X="475" Y="264" T="1781609642690" />
<Point X="477" Y="263" T="1781609642690" />
<Point X="477" Y="262" T="1781609642690" />
<Point X="478" Y="261" T="1781609642691" />
<Point X="480" Y="260" T="1781609642691" />
<Point X="481" Y="259" T="1781609642691" />
<Point X="481" Y="258" T="1781609642692" />
<Point X="482" Y="257" T="1781609642692" />
<Point X="483" Y="256" T="1781609642692" />
<Point X="484" Y="255" T="1781609642692" />
<Point X="485" Y="254" T="1781609642692" />
<Point X="486" Y="253" T="1781609642693" />
<Point X="487" Y="253" T="1781609642693" />
<Point X="487" Y="252" T="1781609642693" />
<Point X="488" Y="251" T="1781609642693" />
<Point X="489" Y="250" T="1781609642693" />
<Point X="490" Y="249" T="1781609642706" />
<Point X="491" Y="248" T="1781609642706" />
<Point X="492" Y="247" T="1781609642707" />
<Point X="492" Y="246" T="1781609642707" />
<Point X="493" Y="245" T="1781609642707" />
<Point X="494" Y="244" T="1781609642707" />
<Point X="494" Y="244" T="1781609642708" />
<Point X="495" Y="243" T="1781609642708" />
<Point X="496" Y="242" T="1781609642708" />
<Point X="496" Y="242" T="1781609642709" />
<Point X="497" Y="241" T="1781609642709" />
<Point X="498" Y="241" T="1781609642709" />
<Point X="498" Y="240" T="1781609642709" />
<Point X="499" Y="239" T="1781609642709" />
<Point X="499" Y="239" T="1781609642710" />
<Point X="500" Y="238" T="1781609642710" />
<Point X="500" Y="238" T="1781609642710" />
<Point X="501" Y="237" T="1781609642723" />
<Point X="501" Y="237" T="1781609642724" />
<Point X="501" Y="236" T="1781609642724" />
<Point X="502" Y="236" T="1781609642724" />
<Point X="502" Y="236" T="1781609642724" />
<Point X="503" Y="235" T="1781609642725" />
<Point X="503" Y="235" T="1781609642725" />
<Point X="503" Y="234" T="1781609642725" />
<Point X="503" Y="234" T="1781609642725" />
<Point X="504" Y="233" T="1781609642725" />
<Point X="504" Y="233" T="1781609642726" />
<Point X="504" Y="233" T="1781609642726" />
<Point X="505" Y="232" T="1781609642726" />
<Point X="505" Y="232" T="1781609642726" />
<Point X="505" Y="232" T="1781609642740" />
<Point X="505" Y="231" T="1781609642740" />
<Point X="506" Y="231" T="1781609642741" />
<Point X="506" Y="231" T="1781609642741" />
<Point X="506" Y="231" T="1781609642741" />
<Point X="506" Y="231" T="1781609642741" />
<Point X="506" Y="230" T="1781609642742" />
<Point X="507" Y="230" T="1781609642742" />
<Point X="507" Y="229" T="1781609642742" />
<Point X="508" Y="229" T="1781609642742" />
<Point X="508" Y="228" T="1781609642742" />
<Point X="508" Y="228" T="1781609642757" />
<Point X="508" Y="228" T="1781609642758" />
<Point X="508" Y="228" T="1781609642758" />
<Point X="509" Y="228" T="1781609642758" />
<Point X="509" Y="227" T="1781609642759" />
<Point X="509" Y="227" T="1781609642759" />
<Point X="509" Y="226" T="1781609642759" />
<Point X="510" Y="226" T="1781609642774" />
<Point X="510" Y="226" T="1781609642774" />
</Gesture>